{"name":"T-UI-18 - Verify that Navigation menu highlights the active page","id":"authentication-module---ui;t-ui-18---verify-that-navigation-menu-highlights-the-active-page","scenarioId":"auth/ui_auth:T-UI-18 - Verify that Navigation menu highlights the active page","methodName":"T-UI-18 - Verify that Navigation menu highlights the active page","testSteps":[{"number":1,"description":"Given I log in as User with username \"testuser\" and password \"test123\"","duration":1194,"startTime":"2026-06-13T05:02:13.606089335Z[Etc/UTC]","result":"SUCCESS","precondition":false,"level":0},{"number":2,"description":"When I force navigate to \"/ui/sales\"","duration":173,"startTime":"2026-06-13T05:02:14.800477437Z[Etc/UTC]","result":"SUCCESS","precondition":false,"level":0},{"number":3,"description":"Then validate the \"Sales\" navigation link should be active","duration":55,"startTime":"2026-06-13T05:02:14.974128337Z[Etc/UTC]","result":"SUCCESS","precondition":false,"level":0}],"userStory":{"id":"auth/ui_auth","storyName":"Authentication Module - UI","displayName":"Authentication Module - UI","path":"auth/ui_auth","pathElements":[{"name":"auth","description":""},{"name":"ui_auth","description":""}],"type":"feature"},"title":"T-UI-18 - Verify that Navigation menu highlights the active page","description":"","coreIssues":["T-UI-18"],"tags":[{"name":"UI","type":"tag","displayName":"UI"},{"name":"Linux","type":"context","displayName":"Linux"},{"name":"215543T","type":"tag","displayName":"215543T"},{"name":"User","type":"tag","displayName":"User"},{"name":"Chrome","type":"context","displayName":"Chrome"},{"name":"Chrome, Linux","type":"context","displayName":"Chrome, Linux"},{"name":"T-UI-18","type":"tag","displayName":"T-UI-18"}],"startTime":"2026-06-13T05:02:13.595563308Z[Etc/UTC]","duration":1204,"projectKey":"","sessionId":"46dddafee066bb5d2d27fc392e0023cd","driver":"chrome","isManualTestingUpToDate":false,"context":"chrome,linux","manual":false,"testSource":"Cucumber","order":0,"result":"SUCCESS","issues":["T-UI-18"]}